PygameManager/Simple.py
PygameManager/__init__.py
pygamemanager-0.0.1.dist-info/METADATA
pygamemanager-0.0.1.dist-info/WHEEL
pygamemanager-0.0.1.dist-info/top_level.txt
pygamemanager-0.0.1.dist-info/RECORD
